Metadata-Version: 2.0
Name: pygments-style-rub
Version: 0.1.2
Summary: Ruhr-Uni Bochum Corporate Design colors for Pygments
Home-page: https://github.com/Holzhaus/pygments-style-rub
Author: Jan Holthuis
Author-email: jan.holthuis@ruhr-uni-bochum.de
License: BSD
Platform: UNKNOWN
Classifier: Development Status :: 4 - Beta
Classifier: Environment :: Plugins
Classifier: Intended Audience :: Developers
Classifier: License :: OSI Approved :: BSD License
Classifier: Operating System :: OS Independent
Classifier: Programming Language :: Python
Classifier: Programming Language :: Python :: 2
Classifier: Programming Language :: Python :: 3
Classifier: Topic :: Software Development :: Libraries :: Python Modules
Requires-Dist: pygments (>=1.4)
